[
    {
        "name": "Crystal-RXXFA",
        "type": "base",
        "hvac": {
            "r": 7.169990821711213,
            "c": 5.396840675508319,
            "p_c": 4.804421391531715,
            "p_h": 8.582651928590508,
            "temp_in_min": 19.35693349044234,
            "temp_in_max": 21.742150470685413,
            "temp_in_sp": 20.549541980563877,
            "temp_in_init": 19.814205279721804
        },
        "wh": {
            "r": 25.09288097120178,
            "c": 5.170480181562655,
            "p": 7.765477864051653,
            "temp_wh_min": 46.024524190322055,
            "temp_wh_max": 49.712932631931636,
            "temp_wh_sp": 47.868728411126845,
            "temp_wh_init": 47.36613783164711,
            "tank_size": 300.0,
            "draw_times": [],
            "draw_sizes": []
        }
    },
    {
        "name": "Myles-XQ5IA",
        "type": "base",
        "hvac": {
            "r": 8.576119271636971,
            "c": 4.2812146969280995,
            "p_c": 8.96596712236991,
            "p_h": 11.240441482789828,
            "temp_in_min": 20.151989702047004,
            "temp_in_max": 22.747731596333914,
            "temp_in_sp": 21.44986064919046,
            "temp_in_init": 21.197007219425828
        },
        "wh": {
            "r": 24.465644838164287,
            "c": 5.177589069109009,
            "p": 7.647712101017152,
            "temp_wh_min": 46.399160337082904,
            "temp_wh_max": 50.49036499107892,
            "temp_wh_sp": 48.44476266408091,
            "temp_wh_init": 47.76382731633427,
            "tank_size": 300.0,
            "draw_times": [],
            "draw_sizes": []
        }
    },
    {
        "name": "Lillie-NMHUH",
        "type": "base",
        "hvac": {
            "r": 7.431956036444323,
            "c": 4.452815267553675,
            "p_c": 3.242949231565225,
            "p_h": 3.3064197747078956,
            "temp_in_min": 20.461147321606422,
            "temp_in_max": 23.07195437711083,
            "temp_in_sp": 21.766550849358627,
            "temp_in_init": 22.515446403059777
        },
        "wh": {
            "r": 24.724374361527442,
            "c": 4.270030133286869,
            "p": 5.153115800075212,
            "temp_wh_min": 43.73855850162742,
            "temp_wh_max": 48.11079197128828,
            "temp_wh_sp": 45.92467523645785,
            "temp_wh_init": 44.20387197758218,
            "tank_size": 300.0,
            "draw_times": [],
            "draw_sizes": []
        }
    },
    {
        "name": "Robert-2D73X",
        "type": "base",
        "hvac": {
            "r": 8.080974544112713,
            "c": 4.424409526102535,
            "p_c": 8.738178321194951,
            "p_h": 5.186847965889756,
            "temp_in_min": 18.48269861944383,
            "temp_in_max": 21.08231780784117,
            "temp_in_sp": 19.7825082136425,
            "temp_in_init": 19.142503270550726
        },
        "wh": {
            "r": 19.821328522150445,
            "c": 5.111649192240604,
            "p": 7.324820646304187,
            "temp_wh_min": 43.77916816466694,
            "temp_wh_max": 47.37855395465377,
            "temp_wh_sp": 45.578861059660355,
            "temp_wh_init": 44.44917806443676,
            "tank_size": 300.0,
            "draw_times": [],
            "draw_sizes": []
        }
    },
    {
        "name": "Serena-98EPE",
        "type": "base",
        "hvac": {
            "r": 6.834979909965007,
            "c": 4.714846376735044,
            "p_c": 4.934751891813743,
            "p_h": 9.379298054382364,
            "temp_in_min": 19.523688531321397,
            "temp_in_max": 21.835972528164646,
            "temp_in_sp": 20.679830529743022,
            "temp_in_init": 19.77684991895391
        },
        "wh": {
            "r": 20.790932144547696,
            "c": 5.416519178119432,
            "p": 5.317685457270378,
            "temp_wh_min": 46.023970460207735,
            "temp_wh_max": 49.45468610713715,
            "temp_wh_sp": 47.73932828367244,
            "temp_wh_init": 47.805365459363365,
            "tank_size": 300.0,
            "draw_times": [],
            "draw_sizes": []
        }
    },
    {
        "name": "Gary-U95TS",
        "type": "base",
        "hvac": {
            "r": 9.004992819439723,
            "c": 5.257178967818004,
            "p_c": 4.968367125856991,
            "p_h": 7.66647901251984,
            "temp_in_min": 20.662385961146423,
            "temp_in_max": 22.73225963590951,
            "temp_in_sp": 21.697322798527967,
            "temp_in_init": 22.588767743048923
        },
        "wh": {
            "r": 20.295749555712813,
            "c": 5.674823115706626,
            "p": 7.71618759988896,
            "temp_wh_min": 45.0614554321895,
            "temp_wh_max": 49.63807301205332,
            "temp_wh_sp": 47.34976422212141,
            "temp_wh_init": 45.5768845343447,
            "tank_size": 300.0,
            "draw_times": [],
            "draw_sizes": []
        }
    },
    {
        "name": "Bruno-PVRNB",
        "type": "base",
        "hvac": {
            "r": 8.961715649880828,
            "c": 4.956844667375021,
            "p_c": 5.242042088091422,
            "p_h": 7.82539487018309,
            "temp_in_min": 19.077326749963223,
            "temp_in_max": 21.87806098417875,
            "temp_in_sp": 20.477693867070986,
            "temp_in_init": 19.431303942400252
        },
        "wh": {
            "r": 21.940302800844886,
            "c": 5.304473259650017,
            "p": 6.7636594541348085,
            "temp_wh_min": 43.52176515188081,
            "temp_wh_max": 48.073463043775625,
            "temp_wh_sp": 45.797614097828216,
            "temp_wh_init": 45.72444823727878,
            "tank_size": 300.0,
            "draw_times": [],
            "draw_sizes": []
        }
    },
    {
        "name": "Dorothy-9XMNY",
        "type": "base",
        "hvac": {
            "r": 6.880211426303227,
            "c": 5.47425244706904,
            "p_c": 4.616062041767407,
            "p_h": 7.306562990758485,
            "temp_in_min": 17.834625905768597,
            "temp_in_max": 20.746059955901913,
            "temp_in_sp": 19.290342930835255,
            "temp_in_init": 19.596059199787277
        },
        "wh": {
            "r": 22.29002650315219,
            "c": 4.424308600171737,
            "p": 7.964269273084756,
            "temp_wh_min": 45.5239820754496,
            "temp_wh_max": 48.607433976693336,
            "temp_wh_sp": 47.06570802607147,
            "temp_wh_init": 48.39618168251015,
            "tank_size": 300.0,
            "draw_times": [],
            "draw_sizes": []
        }
    },
    {
        "name": "Jason-INS3S",
        "type": "base",
        "hvac": {
            "r": 9.09667840706028,
            "c": 4.68438017529583,
            "p_c": 5.258556701207577,
            "p_h": 12.289545350170744,
            "temp_in_min": 18.180567929213055,
            "temp_in_max": 20.375242558255593,
            "temp_in_sp": 19.277905243734324,
            "temp_in_init": 18.817291182771047
        },
        "wh": {
            "r": 21.375998954761066,
            "c": 4.619902217184636,
            "p": 6.285984069548533,
            "temp_wh_min": 44.87681057489171,
            "temp_wh_max": 49.16778131398027,
            "temp_wh_sp": 47.02229594443599,
            "temp_wh_init": 46.58828654331685,
            "tank_size": 300.0,
            "draw_times": [],
            "draw_sizes": []
        }
    },
    {
        "name": "Alvin-4BAYB",
        "type": "base",
        "hvac": {
            "r": 7.1293023712545835,
            "c": 5.349688966419006,
            "p_c": 2.2461778302956334,
            "p_h": 8.966443471059227,
            "temp_in_min": 18.060522920600167,
            "temp_in_max": 20.271130559453052,
            "temp_in_sp": 19.16582674002661,
            "temp_in_init": 19.44553358035005
        },
        "wh": {
            "r": 23.59990806696684,
            "c": 4.878408021076359,
            "p": 6.889549936853421,
            "temp_wh_min": 44.72888597526173,
            "temp_wh_max": 47.98527218027391,
            "temp_wh_sp": 46.35707907776782,
            "temp_wh_init": 45.31631194519155,
            "tank_size": 300.0,
            "draw_times": [],
            "draw_sizes": []
        }
    },
    {
        "name": "Edna-DTGZB",
        "type": "base",
        "hvac": {
            "r": 7.48118804709907,
            "c": 5.303933532882869,
            "p_c": 2.58990868812292,
            "p_h": 8.938589436426867,
            "temp_in_min": 20.64094930377591,
            "temp_in_max": 23.018390086136552,
            "temp_in_sp": 21.82966969495623,
            "temp_in_init": 22.208814331423252
        },
        "wh": {
            "r": 22.948637904050337,
            "c": 5.198047320070759,
            "p": 7.328844002795957,
            "temp_wh_min": 44.19766296488212,
            "temp_wh_max": 48.29296797076673,
            "temp_wh_sp": 46.245315467824426,
            "temp_wh_init": 47.49639854966596,
            "tank_size": 300.0,
            "draw_times": [],
            "draw_sizes": []
        }
    },
    {
        "name": "Emily-V0SNM",
        "type": "base",
        "hvac": {
            "r": 8.254599642461189,
            "c": 4.741354214395135,
            "p_c": 7.12764488699365,
            "p_h": 7.1045263461995924,
            "temp_in_min": 18.422409766752235,
            "temp_in_max": 20.82525697692491,
            "temp_in_sp": 19.623833371838572,
            "temp_in_init": 18.585145385270238
        },
        "wh": {
            "r": 23.051666114716827,
            "c": 4.3932053801973066,
            "p": 5.7794524633028415,
            "temp_wh_min": 44.24952409393488,
            "temp_wh_max": 47.83257098724677,
            "temp_wh_sp": 46.041047540590824,
            "temp_wh_init": 46.616970238323,
            "tank_size": 300.0,
            "draw_times": [],
            "draw_sizes": []
        }
    },
    {
        "name": "Ruth-8R8G7",
        "type": "base",
        "hvac": {
            "r": 9.0661403265273,
            "c": 4.751971293659084,
            "p_c": 6.453399956830072,
            "p_h": 7.520538008259237,
            "temp_in_min": 20.343634442234812,
            "temp_in_max": 23.22881213666761,
            "temp_in_sp": 21.78622328945121,
            "temp_in_init": 21.369150440514677
        },
        "wh": {
            "r": 19.68487632276704,
            "c": 4.835463814134698,
            "p": 6.916739207786472,
            "temp_wh_min": 44.925624084728035,
            "temp_wh_max": 49.577314317122635,
            "temp_wh_sp": 47.251469200925335,
            "temp_wh_init": 47.77913421523661,
            "tank_size": 300.0,
            "draw_times": [],
            "draw_sizes": []
        }
    },
    {
        "name": "Ruth-1HV86",
        "type": "base",
        "hvac": {
            "r": 8.846565298662284,
            "c": 5.717087118524779,
            "p_c": 2.195354522030728,
            "p_h": 12.217146563141469,
            "temp_in_min": 20.327685063642736,
            "temp_in_max": 22.529839407012812,
            "temp_in_sp": 21.428762235327774,
            "temp_in_init": 21.064799144688752
        },
        "wh": {
            "r": 23.62745301271799,
            "c": 4.73295138129609,
            "p": 7.480399925482027,
            "temp_wh_min": 44.364403450108306,
            "temp_wh_max": 47.55910819399748,
            "temp_wh_sp": 45.96175582205289,
            "temp_wh_init": 44.760170358131155,
            "tank_size": 300.0,
            "draw_times": [],
            "draw_sizes": []
        }
    },
    {
        "name": "James-2SIEM",
        "type": "base",
        "hvac": {
            "r": 6.805422160444432,
            "c": 5.186873167603029,
            "p_c": 4.1011904187679065,
            "p_h": 4.397755617292072,
            "temp_in_min": 19.546203250387954,
            "temp_in_max": 21.965218077871704,
            "temp_in_sp": 20.75571066412983,
            "temp_in_init": 19.975593784658013
        },
        "wh": {
            "r": 22.93355413106307,
            "c": 5.706987940891367,
            "p": 6.563915774961288,
            "temp_wh_min": 45.23767085175725,
            "temp_wh_max": 50.032694674474364,
            "temp_wh_sp": 47.63518276311581,
            "temp_wh_init": 46.92332094319017,
            "tank_size": 300.0,
            "draw_times": [],
            "draw_sizes": []
        }
    },
    {
        "name": "Dawn-L23XI",
        "type": "base",
        "hvac": {
            "r": 8.050942465328703,
            "c": 5.675470287049288,
            "p_c": 3.5459676458021985,
            "p_h": 12.862686814797737,
            "temp_in_min": 16.68917228833973,
            "temp_in_max": 19.33713146167899,
            "temp_in_sp": 18.01315187500936,
            "temp_in_init": 16.710364805333572
        },
        "wh": {
            "r": 20.668324792928804,
            "c": 5.703773569417162,
            "p": 6.273455416632658,
            "temp_wh_min": 46.23426807037132,
            "temp_wh_max": 49.91824636234089,
            "temp_wh_sp": 48.076257216356105,
            "temp_wh_init": 47.97715746943666,
            "tank_size": 300.0,
            "draw_times": [],
            "draw_sizes": []
        }
    },
    {
        "name": "Daniel-MYQ0Q",
        "type": "base",
        "hvac": {
            "r": 8.12489031983496,
            "c": 5.401213475930733,
            "p_c": 2.385139953381401,
            "p_h": 2.8449055053360537,
            "temp_in_min": 20.344592522231263,
            "temp_in_max": 22.856235475024594,
            "temp_in_sp": 21.60041399862793,
            "temp_in_init": 20.370810061290893
        },
        "wh": {
            "r": 21.180464109108435,
            "c": 5.3651269523382705,
            "p": 6.593009113412847,
            "temp_wh_min": 45.92723880735305,
            "temp_wh_max": 49.19140941743606,
            "temp_wh_sp": 47.559324112394556,
            "temp_wh_init": 47.162352984940114,
            "tank_size": 300.0,
            "draw_times": [],
            "draw_sizes": []
        }
    },
    {
        "name": "Sylvia-7SZZH",
        "type": "base",
        "hvac": {
            "r": 7.964905792790503,
            "c": 5.48751387982216,
            "p_c": 5.662722495448043,
            "p_h": 8.844253251315042,
            "temp_in_min": 20.51254324109199,
            "temp_in_max": 22.846375726606595,
            "temp_in_sp": 21.679459483849293,
            "temp_in_init": 21.906912008115498
        },
        "wh": {
            "r": 25.22494391015597,
            "c": 5.026533942553202,
            "p": 7.837934368010181,
            "temp_wh_min": 44.33780587802181,
            "temp_wh_max": 48.25297177485133,
            "temp_wh_sp": 46.29538882643657,
            "temp_wh_init": 45.20667384771674,
            "tank_size": 300.0,
            "draw_times": [],
            "draw_sizes": []
        }
    },
    {
        "name": "Joseph-BAAUJ",
        "type": "base",
        "hvac": {
            "r": 8.643521969754612,
            "c": 4.859960452709992,
            "p_c": 4.914587601062271,
            "p_h": 2.3582373147953133,
            "temp_in_min": 16.634400706544263,
            "temp_in_max": 19.41287414040361,
            "temp_in_sp": 18.023637423473936,
            "temp_in_init": 16.869566586823794
        },
        "wh": {
            "r": 20.97432660584746,
            "c": 4.496719934178366,
            "p": 7.997820986432728,
            "temp_wh_min": 45.10666031253832,
            "temp_wh_max": 48.275535928665796,
            "temp_wh_sp": 46.69109812060206,
            "temp_wh_init": 45.825615729776544,
            "tank_size": 300.0,
            "draw_times": [],
            "draw_sizes": []
        }
    },
    {
        "name": "Kayla-P9UW7",
        "type": "base",
        "hvac": {
            "r": 7.185720207501368,
            "c": 4.926962617131972,
            "p_c": 2.3375312487789928,
            "p_h": 9.650460474104076,
            "temp_in_min": 19.50398702645958,
            "temp_in_max": 21.639422161027188,
            "temp_in_sp": 20.571704593743384,
            "temp_in_init": 20.178076070464066
        },
        "wh": {
            "r": 20.966737004298416,
            "c": 5.674072355577461,
            "p": 7.012770766544785,
            "temp_wh_min": 44.798821482392285,
            "temp_wh_max": 49.27927466888117,
            "temp_wh_sp": 47.03904807563673,
            "temp_wh_init": 45.43875629956583,
            "tank_size": 300.0,
            "draw_times": [],
            "draw_sizes": []
        }
    }
]